fh_frankenui/__init__.py
fh_frankenui/_modidx.py
fh_frankenui/core.py
fh_frankenui/foundations.py
fh_frankenui-0.0.3.dist-info/LICENSE
fh_frankenui-0.0.3.dist-info/METADATA
fh_frankenui-0.0.3.dist-info/WHEEL
fh_frankenui-0.0.3.dist-info/entry_points.txt
fh_frankenui-0.0.3.dist-info/top_level.txt
fh_frankenui-0.0.3.dist-info/RECORD
