Metadata-Version: 2.1
Name: fh-frankenui
Version: 0.0.3
Summary: Wrapper for FrankenUI in python
Home-page: https://github.com/Isaac-Flath/fh-frankenui
Author: isaac flath
Author-email: isaac.flath@gmail.com
License: Apache Software License 2.0
Keywords: nbdev jupyter notebook python
Classifier: Development Status :: 4 - Beta
Classifier: Intended Audience :: Developers
Classifier: Natural Language :: English
Classifier: Programming Language :: Python :: 3.7
Classifier: Programming Language :: Python :: 3.8
Classifier: Programming Language :: Python :: 3.9
Classifier: Programming Language :: Python :: 3.10
Classifier: License :: OSI Approved :: Apache Software License
Requires-Python: >=3.7
License-File: LICENSE
Requires-Dist: python-fasthtml
Requires-Dist: fastcore
Provides-Extra: dev
Requires-Dist: pandas; extra == "dev"
Requires-Dist: jinja2; extra == "dev"
Requires-Dist: llms-txt; extra == "dev"
Requires-Dist: pysymbol-llm; extra == "dev"
Requires-Dist: lxml; extra == "dev"
Requires-Dist: mistletoe; extra == "dev"
